prime/__init__.py
prime/agents.py
prime/default_tools.py
prime/e2b_executor.py
prime/gradio_ui.py
prime/local_python_executor.py
prime/models.py
prime/monitoring.py
prime/prompts.py
prime/tool_validation.py
prime/tools.py
prime/types.py
prime/utils.py
prime_agents_py-0.2.0.dist-info/METADATA
prime_agents_py-0.2.0.dist-info/WHEEL
prime_agents_py-0.2.0.dist-info/top_level.txt
prime_agents_py-0.2.0.dist-info/RECORD
