Metadata-Version: 2.1
Name: prime-agents-py
Version: 0.2.0
Summary: Prime is a powerful, modular, and highly extensible framework designed for developers building applications that require a seamless blend of performance, flexibility, and scalability. With Prime, you can harness the power of modern tools to craft cutting-edge solutions across industries.
Author: Prime Inc
Author-email: primengine inc <support@primengine.ai>
Requires-Python: >=3.10
Requires-Dist: torch
Requires-Dist: torchaudio
Requires-Dist: torchvision
Requires-Dist: transformers>=4.0.0
Requires-Dist: requests>=2.32.3
Requires-Dist: rich>=13.9.4
Requires-Dist: pandas>=2.2.3
Requires-Dist: jinja2>=3.1.4
Requires-Dist: pillow>=11.0.0
Requires-Dist: markdownify>=0.14.1
Requires-Dist: gradio>=5.8.0
Requires-Dist: duckduckgo-search>=6.3.7
Requires-Dist: python-dotenv>=1.0.1
Requires-Dist: e2b-code-interpreter>=1.0.3
Requires-Dist: litellm>=1.55.10
Provides-Extra: test
Requires-Dist: pytest>=8.1.0; extra == "test"
Requires-Dist: sqlalchemy; extra == "test"
